{"all_contexts":[
{"num_warnings": 1,
"context":[{"lineno": -1, "instr": "  %5 = alloca %struct.spinlock*, align 8"}, {"lineno": 575, "file": "drivers/net/wireless/ath/ath10k/debugfs_sta.c", "instr": "buf = kzalloc(buf_len, GFP_KERNEL);"}],
"warnings":[{"warn_data": {"at_line": 557, "warn_str": "Trying to use a global variable without locking.", "at": "  %234 = getelementptr [3 x [14 x %struct.kmem_cache*]], [3 x [14 x %struct.kmem_cache*]]* @kmalloc_caches, i64 0, i64 %233, !dbg !18426", "inst_trace": [{"instr_func": "ath10k_dbg_sta_read_tid_stats", "instr_loc": -1, "instr": "  %5 = alloca %struct.spinlock*, align 8"}, {"instr_func": "ath10k_dbg_sta_read_tid_stats", "instr_loc": 575, "instr_file": "drivers/net/wireless/ath/ath10k/debugfs_sta.c", "instr": "buf = kzalloc(buf_len, GFP_KERNEL);"}], "at_file": "./include/linux/slab.h", "by": "GlobalVariableRaceDetector says:", "at_func": "kzalloc"}, "warn_no": 1}]}]}