{"all_contexts":[
{"num_warnings": 2,
"context":[{"lineno": -1, "instr": "  %5 = alloca i64, align 8"}],
"warnings":[{"warn_data": {"at_line": 49, "warn_str": "Potential overflow, using tainted value in binary operation.", "at": "portnum = - portnum;", "inst_trace": [{"instr_func": "companion_store", "instr_loc": -1, "instr": "  %5 = alloca i64, align 8"}, {"instr_func": "companion_store", "instr_loc": 46, "instr_file": "drivers/usb/host/ehci-sysfs.c", "instr": "if (sscanf(buf, \"%d\", &portnum) != 1)"}, {"instr_func": "companion_store", "instr_loc": 49, "instr_file": "drivers/usb/host/ehci-sysfs.c", "instr": "portnum = - portnum;"}], "at_file": "drivers/usb/host/ehci-sysfs.c", "by": "IntegerOverflowDetector says:", "at_func": "companion_store"}, "warn_no": 1},
{"warn_data": {"at_line": 54, "warn_str": "Potential overflow, using tainted value in binary operation.", "at": "portnum--;", "inst_trace": [{"instr_func": "companion_store", "instr_loc": -1, "instr": "  %5 = alloca i64, align 8"}, {"instr_func": "companion_store", "instr_loc": 46, "instr_file": "drivers/usb/host/ehci-sysfs.c", "instr": "if (sscanf(buf, \"%d\", &portnum) != 1)"}, {"instr_func": "companion_store", "instr_loc": 54, "instr_file": "drivers/usb/host/ehci-sysfs.c", "instr": "portnum--;"}], "at_file": "drivers/usb/host/ehci-sysfs.c", "by": "IntegerOverflowDetector says:", "at_func": "companion_store"}, "warn_no": 2}]}]}