{"all_contexts":[
{"num_warnings": 1,
"context":[{"lineno": -1, "instr": "  %4 = alloca i32, align 4"}, {"lineno": 258, "file": "drivers/staging/media/rkvdec/rkvdec.c", "instr": "desc = rkvdec_find_coded_fmt_desc(pix_mp->pixelformat);"}],
"warnings":[{"warn_data": {"at_line": 130, "warn_str": "Trying to use a global variable without locking.", "at": "if (rkvdec_coded_fmts[i].fourcc == fourcc)", "inst_trace": [{"instr_func": "rkvdec_try_output_fmt", "instr_loc": -1, "instr": "  %4 = alloca i32, align 4"}, {"instr_func": "rkvdec_try_output_fmt", "instr_loc": 258, "instr_file": "drivers/staging/media/rkvdec/rkvdec.c", "instr": "desc = rkvdec_find_coded_fmt_desc(pix_mp->pixelformat);"}], "at_file": "drivers/staging/media/rkvdec/rkvdec.c", "by": "GlobalVariableRaceDetector says:", "at_func": "rkvdec_find_coded_fmt_desc"}, "warn_no": 1}]}]}