{"all_contexts":[
{"num_warnings": 1,
"context":[{"lineno": -1, "instr": "  %5 = alloca %struct.file*, align 8"}, {"lineno": 1572, "file": "drivers/net/ethernet/marvell/octeontx2/af/rvu_debugfs.c", "instr": "return rvu_dbg_nix_queue_ctx_write(filp, buffer, count, ppos,"}],
"warnings":[{"warn_data": {"at_line": 1517, "warn_str": "Potential overflow, using tainted value in binary operation.", "at": "cmd_buf = kzalloc(count + 1, GFP_KERNEL);", "inst_trace": [{"instr_func": "rvu_dbg_nix_cq_ctx_write", "instr_loc": -1, "instr": "  %5 = alloca %struct.file*, align 8"}, {"instr_func": "rvu_dbg_nix_cq_ctx_write", "instr_loc": 1571, "instr_file": "drivers/net/ethernet/marvell/octeontx2/af/rvu_debugfs.c", "instr": "{"}, {"instr_func": "rvu_dbg_nix_cq_ctx_write", "instr_loc": 1572, "instr_file": "drivers/net/ethernet/marvell/octeontx2/af/rvu_debugfs.c", "instr": "return rvu_dbg_nix_queue_ctx_write(filp, buffer, count, ppos,"}, {"instr_func": "rvu_dbg_nix_cq_ctx_write", "instr_loc": 1572, "instr_file": "drivers/net/ethernet/marvell/octeontx2/af/rvu_debugfs.c", "instr": "return rvu_dbg_nix_queue_ctx_write(filp, buffer, count, ppos,"}, {"instr_func": "rvu_dbg_nix_queue_ctx_write", "instr_loc": 1492, "instr_file": "drivers/net/ethernet/marvell/octeontx2/af/rvu_debugfs.c", "instr": "{"}, {"instr_func": "rvu_dbg_nix_queue_ctx_write", "instr_loc": 1517, "instr_file": "drivers/net/ethernet/marvell/octeontx2/af/rvu_debugfs.c", "instr": "cmd_buf = kzalloc(count + 1, GFP_KERNEL);"}], "at_file": "drivers/net/ethernet/marvell/octeontx2/af/rvu_debugfs.c", "by": "IntegerOverflowDetector says:", "at_func": "rvu_dbg_nix_queue_ctx_write"}, "warn_no": 1}]},
{"num_warnings": 6,
"context":[{"lineno": -1, "instr": "  %5 = alloca %struct.file*, align 8"}, {"lineno": 1572, "file": "drivers/net/ethernet/marvell/octeontx2/af/rvu_debugfs.c", "instr": "return rvu_dbg_nix_queue_ctx_write(filp, buffer, count, ppos,"}, {"lineno": 1517, "file": "drivers/net/ethernet/marvell/octeontx2/af/rvu_debugfs.c", "instr": "cmd_buf = kzalloc(count + 1, GFP_KERNEL);"}],
"warnings":[{"warn_data": {"at_line": 549, "warn_str": "Potential overflow, using tainted value in binary operation.", "at": "  %44 = sub i64 %43, 1, !dbg !9708", "inst_trace": [{"instr_func": "rvu_dbg_nix_cq_ctx_write", "instr_loc": -1, "instr": "  %5 = alloca %struct.file*, align 8"}, {"instr_func": "rvu_dbg_nix_cq_ctx_write", "instr_loc": 1571, "instr_file": "drivers/net/ethernet/marvell/octeontx2/af/rvu_debugfs.c", "instr": "{"}, {"instr_func": "rvu_dbg_nix_cq_ctx_write", "instr_loc": 1572, "instr_file": "drivers/net/ethernet/marvell/octeontx2/af/rvu_debugfs.c", "instr": "return rvu_dbg_nix_queue_ctx_write(filp, buffer, count, ppos,"}, {"instr_func": "rvu_dbg_nix_cq_ctx_write", "instr_loc": 1572, "instr_file": "drivers/net/ethernet/marvell/octeontx2/af/rvu_debugfs.c", "instr": "return rvu_dbg_nix_queue_ctx_write(filp, buffer, count, ppos,"}, {"instr_func": "rvu_dbg_nix_queue_ctx_write", "instr_loc": 1492, "instr_file": "drivers/net/ethernet/marvell/octeontx2/af/rvu_debugfs.c", "instr": "{"}, {"instr_func": "rvu_dbg_nix_queue_ctx_write", "instr_loc": 1517, "instr_file": "drivers/net/ethernet/marvell/octeontx2/af/rvu_debugfs.c", "instr": "cmd_buf = kzalloc(count + 1, GFP_KERNEL);"}, {"instr_func": "rvu_dbg_nix_queue_ctx_write", "instr_loc": 1517, "instr_file": "drivers/net/ethernet/marvell/octeontx2/af/rvu_debugfs.c", "instr": "cmd_buf = kzalloc(count + 1, GFP_KERNEL);"}, {"instr_func": "rvu_dbg_nix_queue_ctx_write", "instr_loc": 1517, "instr_file": "drivers/net/ethernet/marvell/octeontx2/af/rvu_debugfs.c", "instr": "cmd_buf = kzalloc(count + 1, GFP_KERNEL);"}, {"instr_func": "kzalloc", "instr_loc": 685, "instr_file": "./include/linux/slab.h", "instr": "  store i64 %0, i64* %18, align 8"}, {"instr_func": "kzalloc", "instr_loc": 686, "instr_file": "./include/linux/slab.h", "instr": "  %20 = load i64, i64* %18, align 8, !dbg !9682"}, {"instr_func": "kzalloc", "instr_loc": 685, "instr_file": "./include/linux/slab.h", "instr": "  store i64 %20, i64* %15, align 8"}, {"instr_func": "kzalloc", "instr_loc": 549, "instr_file": "./include/linux/slab.h", "instr": "  %29 = load i64, i64* %15, align 8, !dbg !9691"}, {"instr_func": "kzalloc", "instr_loc": 549, "instr_file": "./include/linux/slab.h", "instr": "  store i64 %29, i64* %11, align 8"}, {"instr_func": "kzalloc", "instr_loc": 484, "instr_file": "./include/linux/slab.h", "instr": "  %31 = load i64, i64* %11, align 8, !dbg !9693"}, {"instr_func": "kzalloc", "instr_loc": 549, "instr_file": "./include/linux/slab.h", "instr": "  store i64 %31, i64* %10, align 8"}, {"instr_func": "kzalloc", "instr_loc": 549, "instr_file": "./include/linux/slab.h", "instr": "  %43 = load i64, i64* %10, align 8, !dbg !9708"}], "at_file": "./include/linux/slab.h", "by": "IntegerOverflowDetector says:", "at_func": "kzalloc"}, "warn_no": 1},
{"warn_data": {"at_line": 557, "warn_str": "Trying to use a global variable without locking.", "at": "  %234 = getelementptr [3 x [14 x %struct.kmem_cache*]], [3 x [14 x %struct.kmem_cache*]]* @kmalloc_caches, i64 0, i64 %233, !dbg !9900", "inst_trace": [{"instr_func": "rvu_dbg_nix_cq_ctx_write", "instr_loc": -1, "instr": "  %5 = alloca %struct.file*, align 8"}, {"instr_func": "rvu_dbg_nix_cq_ctx_write", "instr_loc": 1572, "instr_file": "drivers/net/ethernet/marvell/octeontx2/af/rvu_debugfs.c", "instr": "return rvu_dbg_nix_queue_ctx_write(filp, buffer, count, ppos,"}, {"instr_func": "rvu_dbg_nix_queue_ctx_write", "instr_loc": 1517, "instr_file": "drivers/net/ethernet/marvell/octeontx2/af/rvu_debugfs.c", "instr": "cmd_buf = kzalloc(count + 1, GFP_KERNEL);"}], "at_file": "./include/linux/slab.h", "by": "GlobalVariableRaceDetector says:", "at_func": "kzalloc"}, "warn_no": 2},
{"warn_data": {"at_line": 549, "warn_str": "Potential overflow, using tainted value in binary operation.", "at": "  %69 = add i64 %68, -1, !dbg !9712", "inst_trace": [{"instr_func": "rvu_dbg_nix_cq_ctx_write", "instr_loc": -1, "instr": "  %5 = alloca %struct.file*, align 8"}, {"instr_func": "rvu_dbg_nix_cq_ctx_write", "instr_loc": 1571, "instr_file": "drivers/net/ethernet/marvell/octeontx2/af/rvu_debugfs.c", "instr": "{"}, {"instr_func": "rvu_dbg_nix_cq_ctx_write", "instr_loc": 1572, "instr_file": "drivers/net/ethernet/marvell/octeontx2/af/rvu_debugfs.c", "instr": "return rvu_dbg_nix_queue_ctx_write(filp, buffer, count, ppos,"}, {"instr_func": "rvu_dbg_nix_cq_ctx_write", "instr_loc": 1572, "instr_file": "drivers/net/ethernet/marvell/octeontx2/af/rvu_debugfs.c", "instr": "return rvu_dbg_nix_queue_ctx_write(filp, buffer, count, ppos,"}, {"instr_func": "rvu_dbg_nix_queue_ctx_write", "instr_loc": 1492, "instr_file": "drivers/net/ethernet/marvell/octeontx2/af/rvu_debugfs.c", "instr": "{"}, {"instr_func": "rvu_dbg_nix_queue_ctx_write", "instr_loc": 1517, "instr_file": "drivers/net/ethernet/marvell/octeontx2/af/rvu_debugfs.c", "instr": "cmd_buf = kzalloc(count + 1, GFP_KERNEL);"}, {"instr_func": "rvu_dbg_nix_queue_ctx_write", "instr_loc": 1517, "instr_file": "drivers/net/ethernet/marvell/octeontx2/af/rvu_debugfs.c", "instr": "cmd_buf = kzalloc(count + 1, GFP_KERNEL);"}, {"instr_func": "rvu_dbg_nix_queue_ctx_write", "instr_loc": 1517, "instr_file": "drivers/net/ethernet/marvell/octeontx2/af/rvu_debugfs.c", "instr": "cmd_buf = kzalloc(count + 1, GFP_KERNEL);"}, {"instr_func": "kzalloc", "instr_loc": 685, "instr_file": "./include/linux/slab.h", "instr": "  store i64 %0, i64* %18, align 8"}, {"instr_func": "kzalloc", "instr_loc": 686, "instr_file": "./include/linux/slab.h", "instr": "  %20 = load i64, i64* %18, align 8, !dbg !9682"}, {"instr_func": "kzalloc", "instr_loc": 685, "instr_file": "./include/linux/slab.h", "instr": "  store i64 %20, i64* %15, align 8"}, {"instr_func": "kzalloc", "instr_loc": 549, "instr_file": "./include/linux/slab.h", "instr": "  %29 = load i64, i64* %15, align 8, !dbg !9691"}, {"instr_func": "kzalloc", "instr_loc": 549, "instr_file": "./include/linux/slab.h", "instr": "  store i64 %29, i64* %11, align 8"}, {"instr_func": "kzalloc", "instr_loc": 484, "instr_file": "./include/linux/slab.h", "instr": "  %31 = load i64, i64* %11, align 8, !dbg !9693"}, {"instr_func": "kzalloc", "instr_loc": 549, "instr_file": "./include/linux/slab.h", "instr": "  store i64 %31, i64* %10, align 8"}, {"instr_func": "kzalloc", "instr_loc": 549, "instr_file": "./include/linux/slab.h", "instr": "  %68 = load i64, i64* %10, align 8, !dbg !9712"}], "at_file": "./include/linux/slab.h", "by": "IntegerOverflowDetector says:", "at_func": "kzalloc"}, "warn_no": 3},
{"warn_data": {"at_line": 549, "warn_str": "Potential overflow, using tainted value in binary operation.", "at": "  %61 = sub i64 %60, 1, !dbg !9708", "inst_trace": [{"instr_func": "rvu_dbg_nix_cq_ctx_write", "instr_loc": -1, "instr": "  %5 = alloca %struct.file*, align 8"}, {"instr_func": "rvu_dbg_nix_cq_ctx_write", "instr_loc": 1571, "instr_file": "drivers/net/ethernet/marvell/octeontx2/af/rvu_debugfs.c", "instr": "{"}, {"instr_func": "rvu_dbg_nix_cq_ctx_write", "instr_loc": 1572, "instr_file": "drivers/net/ethernet/marvell/octeontx2/af/rvu_debugfs.c", "instr": "return rvu_dbg_nix_queue_ctx_write(filp, buffer, count, ppos,"}, {"instr_func": "rvu_dbg_nix_cq_ctx_write", "instr_loc": 1572, "instr_file": "drivers/net/ethernet/marvell/octeontx2/af/rvu_debugfs.c", "instr": "return rvu_dbg_nix_queue_ctx_write(filp, buffer, count, ppos,"}, {"instr_func": "rvu_dbg_nix_queue_ctx_write", "instr_loc": 1492, "instr_file": "drivers/net/ethernet/marvell/octeontx2/af/rvu_debugfs.c", "instr": "{"}, {"instr_func": "rvu_dbg_nix_queue_ctx_write", "instr_loc": 1517, "instr_file": "drivers/net/ethernet/marvell/octeontx2/af/rvu_debugfs.c", "instr": "cmd_buf = kzalloc(count + 1, GFP_KERNEL);"}, {"instr_func": "rvu_dbg_nix_queue_ctx_write", "instr_loc": 1517, "instr_file": "drivers/net/ethernet/marvell/octeontx2/af/rvu_debugfs.c", "instr": "cmd_buf = kzalloc(count + 1, GFP_KERNEL);"}, {"instr_func": "rvu_dbg_nix_queue_ctx_write", "instr_loc": 1517, "instr_file": "drivers/net/ethernet/marvell/octeontx2/af/rvu_debugfs.c", "instr": "cmd_buf = kzalloc(count + 1, GFP_KERNEL);"}, {"instr_func": "kzalloc", "instr_loc": 685, "instr_file": "./include/linux/slab.h", "instr": "  store i64 %0, i64* %18, align 8"}, {"instr_func": "kzalloc", "instr_loc": 686, "instr_file": "./include/linux/slab.h", "instr": "  %20 = load i64, i64* %18, align 8, !dbg !9682"}, {"instr_func": "kzalloc", "instr_loc": 685, "instr_file": "./include/linux/slab.h", "instr": "  store i64 %20, i64* %15, align 8"}, {"instr_func": "kzalloc", "instr_loc": 549, "instr_file": "./include/linux/slab.h", "instr": "  %29 = load i64, i64* %15, align 8, !dbg !9691"}, {"instr_func": "kzalloc", "instr_loc": 549, "instr_file": "./include/linux/slab.h", "instr": "  store i64 %29, i64* %11, align 8"}, {"instr_func": "kzalloc", "instr_loc": 484, "instr_file": "./include/linux/slab.h", "instr": "  %31 = load i64, i64* %11, align 8, !dbg !9693"}, {"instr_func": "kzalloc", "instr_loc": 549, "instr_file": "./include/linux/slab.h", "instr": "  store i64 %31, i64* %10, align 8"}, {"instr_func": "kzalloc", "instr_loc": 549, "instr_file": "./include/linux/slab.h", "instr": "  %60 = load i64, i64* %10, align 8, !dbg !9708"}], "at_file": "./include/linux/slab.h", "by": "IntegerOverflowDetector says:", "at_func": "kzalloc"}, "warn_no": 4},
{"warn_data": {"at_line": 549, "warn_str": "Potential overflow, using tainted value in binary operation.", "at": "  %48 = sub i64 %47, 1, !dbg !9708", "inst_trace": [{"instr_func": "rvu_dbg_nix_cq_ctx_write", "instr_loc": -1, "instr": "  %5 = alloca %struct.file*, align 8"}, {"instr_func": "rvu_dbg_nix_cq_ctx_write", "instr_loc": 1571, "instr_file": "drivers/net/ethernet/marvell/octeontx2/af/rvu_debugfs.c", "instr": "{"}, {"instr_func": "rvu_dbg_nix_cq_ctx_write", "instr_loc": 1572, "instr_file": "drivers/net/ethernet/marvell/octeontx2/af/rvu_debugfs.c", "instr": "return rvu_dbg_nix_queue_ctx_write(filp, buffer, count, ppos,"}, {"instr_func": "rvu_dbg_nix_cq_ctx_write", "instr_loc": 1572, "instr_file": "drivers/net/ethernet/marvell/octeontx2/af/rvu_debugfs.c", "instr": "return rvu_dbg_nix_queue_ctx_write(filp, buffer, count, ppos,"}, {"instr_func": "rvu_dbg_nix_queue_ctx_write", "instr_loc": 1492, "instr_file": "drivers/net/ethernet/marvell/octeontx2/af/rvu_debugfs.c", "instr": "{"}, {"instr_func": "rvu_dbg_nix_queue_ctx_write", "instr_loc": 1517, "instr_file": "drivers/net/ethernet/marvell/octeontx2/af/rvu_debugfs.c", "instr": "cmd_buf = kzalloc(count + 1, GFP_KERNEL);"}, {"instr_func": "rvu_dbg_nix_queue_ctx_write", "instr_loc": 1517, "instr_file": "drivers/net/ethernet/marvell/octeontx2/af/rvu_debugfs.c", "instr": "cmd_buf = kzalloc(count + 1, GFP_KERNEL);"}, {"instr_func": "rvu_dbg_nix_queue_ctx_write", "instr_loc": 1517, "instr_file": "drivers/net/ethernet/marvell/octeontx2/af/rvu_debugfs.c", "instr": "cmd_buf = kzalloc(count + 1, GFP_KERNEL);"}, {"instr_func": "kzalloc", "instr_loc": 685, "instr_file": "./include/linux/slab.h", "instr": "  store i64 %0, i64* %18, align 8"}, {"instr_func": "kzalloc", "instr_loc": 686, "instr_file": "./include/linux/slab.h", "instr": "  %20 = load i64, i64* %18, align 8, !dbg !9682"}, {"instr_func": "kzalloc", "instr_loc": 685, "instr_file": "./include/linux/slab.h", "instr": "  store i64 %20, i64* %15, align 8"}, {"instr_func": "kzalloc", "instr_loc": 549, "instr_file": "./include/linux/slab.h", "instr": "  %29 = load i64, i64* %15, align 8, !dbg !9691"}, {"instr_func": "kzalloc", "instr_loc": 549, "instr_file": "./include/linux/slab.h", "instr": "  store i64 %29, i64* %11, align 8"}, {"instr_func": "kzalloc", "instr_loc": 484, "instr_file": "./include/linux/slab.h", "instr": "  %31 = load i64, i64* %11, align 8, !dbg !9693"}, {"instr_func": "kzalloc", "instr_loc": 549, "instr_file": "./include/linux/slab.h", "instr": "  store i64 %31, i64* %10, align 8"}, {"instr_func": "kzalloc", "instr_loc": 549, "instr_file": "./include/linux/slab.h", "instr": "  %47 = load i64, i64* %10, align 8, !dbg !9708"}], "at_file": "./include/linux/slab.h", "by": "IntegerOverflowDetector says:", "at_func": "kzalloc"}, "warn_no": 5},
{"warn_data": {"at_line": 549, "warn_str": "Potential overflow, using tainted value in binary operation.", "at": "  %53 = sub i64 %52, 1, !dbg !9708", "inst_trace": [{"instr_func": "rvu_dbg_nix_cq_ctx_write", "instr_loc": -1, "instr": "  %5 = alloca %struct.file*, align 8"}, {"instr_func": "rvu_dbg_nix_cq_ctx_write", "instr_loc": 1571, "instr_file": "drivers/net/ethernet/marvell/octeontx2/af/rvu_debugfs.c", "instr": "{"}, {"instr_func": "rvu_dbg_nix_cq_ctx_write", "instr_loc": 1572, "instr_file": "drivers/net/ethernet/marvell/octeontx2/af/rvu_debugfs.c", "instr": "return rvu_dbg_nix_queue_ctx_write(filp, buffer, count, ppos,"}, {"instr_func": "rvu_dbg_nix_cq_ctx_write", "instr_loc": 1572, "instr_file": "drivers/net/ethernet/marvell/octeontx2/af/rvu_debugfs.c", "instr": "return rvu_dbg_nix_queue_ctx_write(filp, buffer, count, ppos,"}, {"instr_func": "rvu_dbg_nix_queue_ctx_write", "instr_loc": 1492, "instr_file": "drivers/net/ethernet/marvell/octeontx2/af/rvu_debugfs.c", "instr": "{"}, {"instr_func": "rvu_dbg_nix_queue_ctx_write", "instr_loc": 1517, "instr_file": "drivers/net/ethernet/marvell/octeontx2/af/rvu_debugfs.c", "instr": "cmd_buf = kzalloc(count + 1, GFP_KERNEL);"}, {"instr_func": "rvu_dbg_nix_queue_ctx_write", "instr_loc": 1517, "instr_file": "drivers/net/ethernet/marvell/octeontx2/af/rvu_debugfs.c", "instr": "cmd_buf = kzalloc(count + 1, GFP_KERNEL);"}, {"instr_func": "rvu_dbg_nix_queue_ctx_write", "instr_loc": 1517, "instr_file": "drivers/net/ethernet/marvell/octeontx2/af/rvu_debugfs.c", "instr": "cmd_buf = kzalloc(count + 1, GFP_KERNEL);"}, {"instr_func": "kzalloc", "instr_loc": 685, "instr_file": "./include/linux/slab.h", "instr": "  store i64 %0, i64* %18, align 8"}, {"instr_func": "kzalloc", "instr_loc": 686, "instr_file": "./include/linux/slab.h", "instr": "  %20 = load i64, i64* %18, align 8, !dbg !9682"}, {"instr_func": "kzalloc", "instr_loc": 685, "instr_file": "./include/linux/slab.h", "instr": "  store i64 %20, i64* %15, align 8"}, {"instr_func": "kzalloc", "instr_loc": 549, "instr_file": "./include/linux/slab.h", "instr": "  %29 = load i64, i64* %15, align 8, !dbg !9691"}, {"instr_func": "kzalloc", "instr_loc": 549, "instr_file": "./include/linux/slab.h", "instr": "  store i64 %29, i64* %11, align 8"}, {"instr_func": "kzalloc", "instr_loc": 484, "instr_file": "./include/linux/slab.h", "instr": "  %31 = load i64, i64* %11, align 8, !dbg !9693"}, {"instr_func": "kzalloc", "instr_loc": 549, "instr_file": "./include/linux/slab.h", "instr": "  store i64 %31, i64* %10, align 8"}, {"instr_func": "kzalloc", "instr_loc": 549, "instr_file": "./include/linux/slab.h", "instr": "  %52 = load i64, i64* %10, align 8, !dbg !9708"}], "at_file": "./include/linux/slab.h", "by": "IntegerOverflowDetector says:", "at_func": "kzalloc"}, "warn_no": 6}]},
{"num_warnings": 3,
"context":[{"lineno": -1, "instr": "  %5 = alloca %struct.file*, align 8"}, {"lineno": 1572, "file": "drivers/net/ethernet/marvell/octeontx2/af/rvu_debugfs.c", "instr": "return rvu_dbg_nix_queue_ctx_write(filp, buffer, count, ppos,"}, {"lineno": 1522, "file": "drivers/net/ethernet/marvell/octeontx2/af/rvu_debugfs.c", "instr": "ret = parse_cmd_buffer_ctx(cmd_buf, &count, buffer,"}],
"warnings":[{"warn_data": {"at_line": 782, "warn_str": "Non-constant size used in copy_to(or from)_user function.", "at": "{", "inst_trace": [], "at_file": "drivers/net/ethernet/marvell/octeontx2/af/rvu_debugfs.c", "by": "TaintedSizeDetector says:", "at_func": "parse_cmd_buffer_ctx"}, "warn_no": 1},
{"warn_data": {"at_line": 793, "warn_str": "Tainted Data used in risky function", "at": "cmd_buf_tmp = strchr(cmd_buf, '\\n');", "inst_trace": [{"instr_func": "parse_cmd_buffer_ctx", "instr_loc": 782, "instr_file": "drivers/net/ethernet/marvell/octeontx2/af/rvu_debugfs.c", "instr": "{"}], "at_file": "drivers/net/ethernet/marvell/octeontx2/af/rvu_debugfs.c", "by": "ImproperTaintedDataUseDetector says:", "tainted_obj": "  %83 = call noalias i8* @kmalloc_order_trace(i64 %80, i32 %81, i32 %82) #13, !dbg !9725", "at_func": "parse_cmd_buffer_ctx"}, "warn_no": 2},
{"warn_data": {"at_line": 792, "warn_str": "Trying to write to a user pointer.", "at": "cmd_buf[*count] = '\\0';", "inst_trace": [{"instr_func": "rvu_dbg_nix_cq_ctx_write", "instr_loc": -1, "instr": "  %5 = alloca %struct.file*, align 8"}, {"instr_func": "rvu_dbg_nix_cq_ctx_write", "instr_loc": 1571, "instr_file": "drivers/net/ethernet/marvell/octeontx2/af/rvu_debugfs.c", "instr": "{"}, {"instr_func": "rvu_dbg_nix_cq_ctx_write", "instr_loc": 1572, "instr_file": "drivers/net/ethernet/marvell/octeontx2/af/rvu_debugfs.c", "instr": "return rvu_dbg_nix_queue_ctx_write(filp, buffer, count, ppos,"}, {"instr_func": "rvu_dbg_nix_cq_ctx_write", "instr_loc": 1572, "instr_file": "drivers/net/ethernet/marvell/octeontx2/af/rvu_debugfs.c", "instr": "return rvu_dbg_nix_queue_ctx_write(filp, buffer, count, ppos,"}, {"instr_func": "rvu_dbg_nix_queue_ctx_write", "instr_loc": 1492, "instr_file": "drivers/net/ethernet/marvell/octeontx2/af/rvu_debugfs.c", "instr": "{"}, {"instr_func": "parse_cmd_buffer_ctx", "instr_loc": 792, "instr_file": "drivers/net/ethernet/marvell/octeontx2/af/rvu_debugfs.c", "instr": "cmd_buf[*count] = '\\0';"}, {"instr_func": "parse_cmd_buffer_ctx", "instr_loc": 792, "instr_file": "drivers/net/ethernet/marvell/octeontx2/af/rvu_debugfs.c", "instr": "cmd_buf[*count] = '\\0';"}], "at_file": "drivers/net/ethernet/marvell/octeontx2/af/rvu_debugfs.c", "by": "TaintedPointerDereferenceChecker says:", "at_func": "parse_cmd_buffer_ctx"}, "warn_no": 3}]}]}