{"all_contexts":[
{"num_warnings": 2,
"context":[{"lineno": -1, "instr": "  %5 = alloca i64, align 8"}],
"warnings":[{"warn_data": {"at_line": 364, "warn_str": "Trying to use a global variable without locking.", "at": "if (!nowayout) {", "inst_trace": [{"instr_func": "usb_pcwd_write", "instr_loc": -1, "instr": "  %5 = alloca i64, align 8"}], "at_file": "drivers/watchdog/pcwd_usb.c", "by": "GlobalVariableRaceDetector says:", "at_func": "usb_pcwd_write"}, "warn_no": 1},
{"warn_data": {"at_line": 373, "warn_str": "Loop is bounded by a tainted value.", "at": "for (i = 0; i != len; i++) {", "inst_trace": [{"instr_func": "usb_pcwd_write", "instr_loc": -1, "instr": "  %5 = alloca i64, align 8"}, {"instr_func": "usb_pcwd_write", "instr_loc": 361, "instr_file": "drivers/watchdog/pcwd_usb.c", "instr": "{"}, {"instr_func": "usb_pcwd_write", "instr_loc": 373, "instr_file": "drivers/watchdog/pcwd_usb.c", "instr": "for (i = 0; i != len; i++) {"}, {"instr_func": "usb_pcwd_write", "instr_loc": 373, "instr_file": "drivers/watchdog/pcwd_usb.c", "instr": "for (i = 0; i != len; i++) {"}], "at_file": "drivers/watchdog/pcwd_usb.c", "by": "TaintedLoopBoundDetector says:", "at_func": "usb_pcwd_write"}, "warn_no": 2}]},
{"num_warnings": 1,
"context":[{"lineno": -1, "instr": "  %5 = alloca i64, align 8"}, {"lineno": 383, "file": "drivers/watchdog/pcwd_usb.c", "instr": "usb_pcwd_keepalive(usb_pcwd_device);"}, {"lineno": 305, "file": "drivers/watchdog/pcwd_usb.c", "instr": "usb_pcwd_send_command(usb_pcwd, CMD_TRIGGER, &dummy, &dummy);"}],
"warnings":[{"warn_data": {"at_line": 215, "warn_str": "Trying to use a global variable without locking.", "at": "if ((!usb_pcwd) || (!usb_pcwd->exists))", "inst_trace": [{"instr_func": "usb_pcwd_write", "instr_loc": -1, "instr": "  %5 = alloca i64, align 8"}, {"instr_func": "usb_pcwd_write", "instr_loc": 383, "instr_file": "drivers/watchdog/pcwd_usb.c", "instr": "usb_pcwd_keepalive(usb_pcwd_device);"}, {"instr_func": "usb_pcwd_keepalive", "instr_loc": 305, "instr_file": "drivers/watchdog/pcwd_usb.c", "instr": "usb_pcwd_send_command(usb_pcwd, CMD_TRIGGER, &dummy, &dummy);"}], "at_file": "drivers/watchdog/pcwd_usb.c", "by": "GlobalVariableRaceDetector says:", "at_func": "usb_pcwd_send_command"}, "warn_no": 1}]}]}