{"all_contexts":[
{"num_warnings": 10,
"context":[{"lineno": -1, "instr": "  %5 = alloca i8*, align 8"}],
"warnings":[{"warn_data": {"at_line": 640, "warn_str": "Potential overflow, using tainted value in binary operation.", "at": "aligned_count = count + unaligned_bytes;", "inst_trace": [{"instr_func": "wil_read_file_ioblob", "instr_loc": -1, "instr": "  %5 = alloca i8*, align 8"}, {"instr_func": "wil_read_file_ioblob", "instr_loc": 616, "instr_file": "drivers/net/wireless/ath/wil6210/debugfs.c", "instr": "{"}, {"instr_func": "wil_read_file_ioblob", "instr_loc": 640, "instr_file": "drivers/net/wireless/ath/wil6210/debugfs.c", "instr": "aligned_count = count + unaligned_bytes;"}], "at_file": "drivers/net/wireless/ath/wil6210/debugfs.c", "by": "IntegerOverflowDetector says:", "at_func": "wil_read_file_ioblob"}, "warn_no": 1},
{"warn_data": {"at_line": 638, "warn_str": "Trying to use a global variable without locking.", "at": "unaligned_bytes = pos % 4;", "inst_trace": [{"instr_func": "wil_read_file_ioblob", "instr_loc": -1, "instr": "  %5 = alloca i8*, align 8"}], "at_file": "drivers/net/wireless/ath/wil6210/debugfs.c", "by": "GlobalVariableRaceDetector says:", "at_func": "wil_read_file_ioblob"}, "warn_no": 2},
{"warn_data": {"at_line": 638, "warn_str": "Potential overflow, using tainted value in binary operation.", "at": "unaligned_bytes = pos % 4;", "inst_trace": [{"instr_func": "wil_read_file_ioblob", "instr_loc": -1, "instr": "  %5 = alloca i8*, align 8"}, {"instr_func": "wil_read_file_ioblob", "instr_loc": 616, "instr_file": "drivers/net/wireless/ath/wil6210/debugfs.c", "instr": "{"}, {"instr_func": "wil_read_file_ioblob", "instr_loc": 640, "instr_file": "drivers/net/wireless/ath/wil6210/debugfs.c", "instr": "aligned_count = count + unaligned_bytes;"}, {"instr_func": "wil_read_file_ioblob", "instr_loc": 640, "instr_file": "drivers/net/wireless/ath/wil6210/debugfs.c", "instr": "aligned_count = count + unaligned_bytes;"}, {"instr_func": "wil_read_file_ioblob", "instr_loc": 640, "instr_file": "drivers/net/wireless/ath/wil6210/debugfs.c", "instr": "aligned_count = count + unaligned_bytes;"}, {"instr_func": "wil_read_file_ioblob", "instr_loc": 642, "instr_file": "drivers/net/wireless/ath/wil6210/debugfs.c", "instr": "buf = kmalloc(aligned_count, GFP_KERNEL);"}, {"instr_func": "wil_read_file_ioblob", "instr_loc": 638, "instr_file": "drivers/net/wireless/ath/wil6210/debugfs.c", "instr": "unaligned_bytes = pos % 4;"}, {"instr_func": "wil_read_file_ioblob", "instr_loc": 638, "instr_file": "drivers/net/wireless/ath/wil6210/debugfs.c", "instr": "unaligned_bytes = pos % 4;"}, {"instr_func": "wil_read_file_ioblob", "instr_loc": 638, "instr_file": "drivers/net/wireless/ath/wil6210/debugfs.c", "instr": "unaligned_bytes = pos % 4;"}, {"instr_func": "wil_read_file_ioblob", "instr_loc": 638, "instr_file": "drivers/net/wireless/ath/wil6210/debugfs.c", "instr": "unaligned_bytes = pos % 4;"}, {"instr_func": "wil_read_file_ioblob", "instr_loc": 638, "instr_file": "drivers/net/wireless/ath/wil6210/debugfs.c", "instr": "unaligned_bytes = pos % 4;"}, {"instr_func": "wil_read_file_ioblob", "instr_loc": 638, "instr_file": "drivers/net/wireless/ath/wil6210/debugfs.c", "instr": "unaligned_bytes = pos % 4;"}], "at_file": "drivers/net/wireless/ath/wil6210/debugfs.c", "by": "IntegerOverflowDetector says:", "at_func": "wil_read_file_ioblob"}, "warn_no": 3},
{"warn_data": {"at_line": 638, "warn_str": "Potential overflow, using tainted value in binary operation.", "at": "unaligned_bytes = pos % 4;", "inst_trace": [{"instr_func": "wil_read_file_ioblob", "instr_loc": -1, "instr": "  %5 = alloca i8*, align 8"}, {"instr_func": "wil_read_file_ioblob", "instr_loc": 616, "instr_file": "drivers/net/wireless/ath/wil6210/debugfs.c", "instr": "{"}, {"instr_func": "wil_read_file_ioblob", "instr_loc": 640, "instr_file": "drivers/net/wireless/ath/wil6210/debugfs.c", "instr": "aligned_count = count + unaligned_bytes;"}, {"instr_func": "wil_read_file_ioblob", "instr_loc": 640, "instr_file": "drivers/net/wireless/ath/wil6210/debugfs.c", "instr": "aligned_count = count + unaligned_bytes;"}, {"instr_func": "wil_read_file_ioblob", "instr_loc": 640, "instr_file": "drivers/net/wireless/ath/wil6210/debugfs.c", "instr": "aligned_count = count + unaligned_bytes;"}, {"instr_func": "wil_read_file_ioblob", "instr_loc": 642, "instr_file": "drivers/net/wireless/ath/wil6210/debugfs.c", "instr": "buf = kmalloc(aligned_count, GFP_KERNEL);"}, {"instr_func": "wil_read_file_ioblob", "instr_loc": 638, "instr_file": "drivers/net/wireless/ath/wil6210/debugfs.c", "instr": "unaligned_bytes = pos % 4;"}, {"instr_func": "wil_read_file_ioblob", "instr_loc": 638, "instr_file": "drivers/net/wireless/ath/wil6210/debugfs.c", "instr": "unaligned_bytes = pos % 4;"}, {"instr_func": "wil_read_file_ioblob", "instr_loc": 638, "instr_file": "drivers/net/wireless/ath/wil6210/debugfs.c", "instr": "unaligned_bytes = pos % 4;"}, {"instr_func": "wil_read_file_ioblob", "instr_loc": 638, "instr_file": "drivers/net/wireless/ath/wil6210/debugfs.c", "instr": "unaligned_bytes = pos % 4;"}, {"instr_func": "wil_read_file_ioblob", "instr_loc": 638, "instr_file": "drivers/net/wireless/ath/wil6210/debugfs.c", "instr": "unaligned_bytes = pos % 4;"}, {"instr_func": "wil_read_file_ioblob", "instr_loc": 638, "instr_file": "drivers/net/wireless/ath/wil6210/debugfs.c", "instr": "unaligned_bytes = pos % 4;"}], "at_file": "drivers/net/wireless/ath/wil6210/debugfs.c", "by": "IntegerOverflowDetector says:", "at_func": "wil_read_file_ioblob"}, "warn_no": 4},
{"warn_data": {"at_line": 638, "warn_str": "Potential overflow, using tainted value in binary operation.", "at": "unaligned_bytes = pos % 4;", "inst_trace": [{"instr_func": "wil_read_file_ioblob", "instr_loc": -1, "instr": "  %5 = alloca i8*, align 8"}, {"instr_func": "wil_read_file_ioblob", "instr_loc": 616, "instr_file": "drivers/net/wireless/ath/wil6210/debugfs.c", "instr": "{"}, {"instr_func": "wil_read_file_ioblob", "instr_loc": 640, "instr_file": "drivers/net/wireless/ath/wil6210/debugfs.c", "instr": "aligned_count = count + unaligned_bytes;"}, {"instr_func": "wil_read_file_ioblob", "instr_loc": 640, "instr_file": "drivers/net/wireless/ath/wil6210/debugfs.c", "instr": "aligned_count = count + unaligned_bytes;"}, {"instr_func": "wil_read_file_ioblob", "instr_loc": 640, "instr_file": "drivers/net/wireless/ath/wil6210/debugfs.c", "instr": "aligned_count = count + unaligned_bytes;"}, {"instr_func": "wil_read_file_ioblob", "instr_loc": 642, "instr_file": "drivers/net/wireless/ath/wil6210/debugfs.c", "instr": "buf = kmalloc(aligned_count, GFP_KERNEL);"}, {"instr_func": "wil_read_file_ioblob", "instr_loc": 638, "instr_file": "drivers/net/wireless/ath/wil6210/debugfs.c", "instr": "unaligned_bytes = pos % 4;"}, {"instr_func": "wil_read_file_ioblob", "instr_loc": 638, "instr_file": "drivers/net/wireless/ath/wil6210/debugfs.c", "instr": "unaligned_bytes = pos % 4;"}, {"instr_func": "wil_read_file_ioblob", "instr_loc": 638, "instr_file": "drivers/net/wireless/ath/wil6210/debugfs.c", "instr": "unaligned_bytes = pos % 4;"}, {"instr_func": "wil_read_file_ioblob", "instr_loc": 638, "instr_file": "drivers/net/wireless/ath/wil6210/debugfs.c", "instr": "unaligned_bytes = pos % 4;"}, {"instr_func": "wil_read_file_ioblob", "instr_loc": 638, "instr_file": "drivers/net/wireless/ath/wil6210/debugfs.c", "instr": "unaligned_bytes = pos % 4;"}, {"instr_func": "wil_read_file_ioblob", "instr_loc": 638, "instr_file": "drivers/net/wireless/ath/wil6210/debugfs.c", "instr": "unaligned_bytes = pos % 4;"}], "at_file": "drivers/net/wireless/ath/wil6210/debugfs.c", "by": "IntegerOverflowDetector says:", "at_func": "wil_read_file_ioblob"}, "warn_no": 5},
{"warn_data": {"at_line": 638, "warn_str": "Potential overflow, using tainted value in binary operation.", "at": "unaligned_bytes = pos % 4;", "inst_trace": [{"instr_func": "wil_read_file_ioblob", "instr_loc": -1, "instr": "  %5 = alloca i8*, align 8"}, {"instr_func": "wil_read_file_ioblob", "instr_loc": 616, "instr_file": "drivers/net/wireless/ath/wil6210/debugfs.c", "instr": "{"}, {"instr_func": "wil_read_file_ioblob", "instr_loc": 640, "instr_file": "drivers/net/wireless/ath/wil6210/debugfs.c", "instr": "aligned_count = count + unaligned_bytes;"}, {"instr_func": "wil_read_file_ioblob", "instr_loc": 640, "instr_file": "drivers/net/wireless/ath/wil6210/debugfs.c", "instr": "aligned_count = count + unaligned_bytes;"}, {"instr_func": "wil_read_file_ioblob", "instr_loc": 640, "instr_file": "drivers/net/wireless/ath/wil6210/debugfs.c", "instr": "aligned_count = count + unaligned_bytes;"}, {"instr_func": "wil_read_file_ioblob", "instr_loc": 642, "instr_file": "drivers/net/wireless/ath/wil6210/debugfs.c", "instr": "buf = kmalloc(aligned_count, GFP_KERNEL);"}, {"instr_func": "wil_read_file_ioblob", "instr_loc": 638, "instr_file": "drivers/net/wireless/ath/wil6210/debugfs.c", "instr": "unaligned_bytes = pos % 4;"}, {"instr_func": "wil_read_file_ioblob", "instr_loc": 638, "instr_file": "drivers/net/wireless/ath/wil6210/debugfs.c", "instr": "unaligned_bytes = pos % 4;"}, {"instr_func": "wil_read_file_ioblob", "instr_loc": 638, "instr_file": "drivers/net/wireless/ath/wil6210/debugfs.c", "instr": "unaligned_bytes = pos % 4;"}, {"instr_func": "wil_read_file_ioblob", "instr_loc": 638, "instr_file": "drivers/net/wireless/ath/wil6210/debugfs.c", "instr": "unaligned_bytes = pos % 4;"}, {"instr_func": "wil_read_file_ioblob", "instr_loc": 638, "instr_file": "drivers/net/wireless/ath/wil6210/debugfs.c", "instr": "unaligned_bytes = pos % 4;"}, {"instr_func": "wil_read_file_ioblob", "instr_loc": 638, "instr_file": "drivers/net/wireless/ath/wil6210/debugfs.c", "instr": "unaligned_bytes = pos % 4;"}], "at_file": "drivers/net/wireless/ath/wil6210/debugfs.c", "by": "IntegerOverflowDetector says:", "at_func": "wil_read_file_ioblob"}, "warn_no": 6},
{"warn_data": {"at_line": 638, "warn_str": "Potential overflow, using tainted value in binary operation.", "at": "unaligned_bytes = pos % 4;", "inst_trace": [{"instr_func": "wil_read_file_ioblob", "instr_loc": -1, "instr": "  %5 = alloca i8*, align 8"}, {"instr_func": "wil_read_file_ioblob", "instr_loc": 616, "instr_file": "drivers/net/wireless/ath/wil6210/debugfs.c", "instr": "{"}, {"instr_func": "wil_read_file_ioblob", "instr_loc": 640, "instr_file": "drivers/net/wireless/ath/wil6210/debugfs.c", "instr": "aligned_count = count + unaligned_bytes;"}, {"instr_func": "wil_read_file_ioblob", "instr_loc": 640, "instr_file": "drivers/net/wireless/ath/wil6210/debugfs.c", "instr": "aligned_count = count + unaligned_bytes;"}, {"instr_func": "wil_read_file_ioblob", "instr_loc": 640, "instr_file": "drivers/net/wireless/ath/wil6210/debugfs.c", "instr": "aligned_count = count + unaligned_bytes;"}, {"instr_func": "wil_read_file_ioblob", "instr_loc": 642, "instr_file": "drivers/net/wireless/ath/wil6210/debugfs.c", "instr": "buf = kmalloc(aligned_count, GFP_KERNEL);"}, {"instr_func": "wil_read_file_ioblob", "instr_loc": 638, "instr_file": "drivers/net/wireless/ath/wil6210/debugfs.c", "instr": "unaligned_bytes = pos % 4;"}, {"instr_func": "wil_read_file_ioblob", "instr_loc": 638, "instr_file": "drivers/net/wireless/ath/wil6210/debugfs.c", "instr": "unaligned_bytes = pos % 4;"}, {"instr_func": "wil_read_file_ioblob", "instr_loc": 638, "instr_file": "drivers/net/wireless/ath/wil6210/debugfs.c", "instr": "unaligned_bytes = pos % 4;"}, {"instr_func": "wil_read_file_ioblob", "instr_loc": 638, "instr_file": "drivers/net/wireless/ath/wil6210/debugfs.c", "instr": "unaligned_bytes = pos % 4;"}, {"instr_func": "wil_read_file_ioblob", "instr_loc": 638, "instr_file": "drivers/net/wireless/ath/wil6210/debugfs.c", "instr": "unaligned_bytes = pos % 4;"}, {"instr_func": "wil_read_file_ioblob", "instr_loc": 638, "instr_file": "drivers/net/wireless/ath/wil6210/debugfs.c", "instr": "unaligned_bytes = pos % 4;"}], "at_file": "drivers/net/wireless/ath/wil6210/debugfs.c", "by": "IntegerOverflowDetector says:", "at_func": "wil_read_file_ioblob"}, "warn_no": 7},
{"warn_data": {"at_line": 671, "warn_str": "Potential overflow, using tainted value in binary operation.", "at": "count -= ret;", "inst_trace": [{"instr_func": "wil_read_file_ioblob", "instr_loc": -1, "instr": "  %5 = alloca i8*, align 8"}, {"instr_func": "wil_read_file_ioblob", "instr_loc": 616, "instr_file": "drivers/net/wireless/ath/wil6210/debugfs.c", "instr": "{"}, {"instr_func": "wil_read_file_ioblob", "instr_loc": 662, "instr_file": "drivers/net/wireless/ath/wil6210/debugfs.c", "instr": "ret = copy_to_user(user_buf, buf + unaligned_bytes, count);"}, {"instr_func": "wil_read_file_ioblob", "instr_loc": 659, "instr_file": "drivers/net/wireless/ath/wil6210/debugfs.c", "instr": "wil_memcpy_fromio_32(buf, (const void __iomem *)"}, {"instr_func": "wil_read_file_ioblob", "instr_loc": 659, "instr_file": "drivers/net/wireless/ath/wil6210/debugfs.c", "instr": "wil_memcpy_fromio_32(buf, (const void __iomem *)"}, {"instr_func": "wil_read_file_ioblob", "instr_loc": 662, "instr_file": "drivers/net/wireless/ath/wil6210/debugfs.c", "instr": "ret = copy_to_user(user_buf, buf + unaligned_bytes, count);"}, {"instr_func": "wil_read_file_ioblob", "instr_loc": 671, "instr_file": "drivers/net/wireless/ath/wil6210/debugfs.c", "instr": "count -= ret;"}], "at_file": "drivers/net/wireless/ath/wil6210/debugfs.c", "by": "IntegerOverflowDetector says:", "at_func": "wil_read_file_ioblob"}, "warn_no": 8},
{"warn_data": {"at_line": 659, "warn_str": "Non-constant size used in copy_to(or from)_user function.", "at": "wil_memcpy_fromio_32(buf, (const void __iomem *)", "inst_trace": [], "at_file": "drivers/net/wireless/ath/wil6210/debugfs.c", "by": "TaintedSizeDetector says:", "at_func": "wil_read_file_ioblob"}, "warn_no": 9},
{"warn_data": {"at_line": 672, "warn_str": "Potential overflow, using tainted value in binary operation.", "at": "*ppos = pos + count;", "inst_trace": [{"instr_func": "wil_read_file_ioblob", "instr_loc": -1, "instr": "  %5 = alloca i8*, align 8"}, {"instr_func": "wil_read_file_ioblob", "instr_loc": 616, "instr_file": "drivers/net/wireless/ath/wil6210/debugfs.c", "instr": "{"}, {"instr_func": "wil_read_file_ioblob", "instr_loc": 672, "instr_file": "drivers/net/wireless/ath/wil6210/debugfs.c", "instr": "*ppos = pos + count;"}], "at_file": "drivers/net/wireless/ath/wil6210/debugfs.c", "by": "IntegerOverflowDetector says:", "at_func": "wil_read_file_ioblob"}, "warn_no": 10}]}]}