{"all_contexts":[
{"num_warnings": 1,
"context":[{"lineno": -1, "instr": "  %5 = alloca i64, align 8"}],
"warnings":[{"warn_data": {"at_line": 1138, "warn_str": "Loop is bounded by a tainted value.", "at": "if (i2c_encode_flags_to_addr(client) == addr) {", "inst_trace": [{"instr_func": "i2c_sysfs_delete_device", "instr_loc": -1, "instr": "  %5 = alloca i64, align 8"}, {"instr_func": "i2c_sysfs_delete_device", "instr_loc": 1122, "instr_file": "drivers/i2c/i2c-core-base.c", "instr": "res = sscanf(buf, \"%hi%c\", &addr, &end);"}, {"instr_func": "i2c_sysfs_delete_device", "instr_loc": 1138, "instr_file": "drivers/i2c/i2c-core-base.c", "instr": "if (i2c_encode_flags_to_addr(client) == addr) {"}, {"instr_func": "i2c_sysfs_delete_device", "instr_loc": 1138, "instr_file": "drivers/i2c/i2c-core-base.c", "instr": "if (i2c_encode_flags_to_addr(client) == addr) {"}], "at_file": "drivers/i2c/i2c-core-base.c", "by": "TaintedLoopBoundDetector says:", "at_func": "i2c_sysfs_delete_device"}, "warn_no": 1}]},
{"num_warnings": 1,
"context":[{"lineno": -1, "instr": "  %5 = alloca i64, align 8"}, {"lineno": 1135, "file": "drivers/i2c/i2c-core-base.c", "instr": "i2c_adapter_depth(adap));"}],
"warnings":[{"warn_data": {"at_line": 1026, "warn_str": "Trying to use a global variable without locking.", "at": "WARN_ONCE(depth >= MAX_LOCKDEP_SUBCLASSES,", "inst_trace": [{"instr_func": "i2c_sysfs_delete_device", "instr_loc": -1, "instr": "  %5 = alloca i64, align 8"}, {"instr_func": "i2c_sysfs_delete_device", "instr_loc": 1135, "instr_file": "drivers/i2c/i2c-core-base.c", "instr": "i2c_adapter_depth(adap));"}], "at_file": "drivers/i2c/i2c-core-base.c", "by": "GlobalVariableRaceDetector says:", "at_func": "i2c_adapter_depth"}, "warn_no": 1}]},
{"num_warnings": 1,
"context":[{"lineno": -1, "instr": "  %5 = alloca i64, align 8"}, {"lineno": 1135, "file": "drivers/i2c/i2c-core-base.c", "instr": "i2c_adapter_depth(adap));"}, {"lineno": 1023, "file": "drivers/i2c/i2c-core-base.c", "instr": "while ((adapter = i2c_parent_is_i2c_adapter(adapter)))"}],
"warnings":[{"warn_data": {"at_line": 733, "warn_str": "Trying to use a global variable without locking.", "at": "  %18 = icmp eq %struct.device_type.1942* %17, @i2c_adapter_type, !dbg !59804", "inst_trace": [{"instr_func": "i2c_sysfs_delete_device", "instr_loc": -1, "instr": "  %5 = alloca i64, align 8"}, {"instr_func": "i2c_sysfs_delete_device", "instr_loc": 1135, "instr_file": "drivers/i2c/i2c-core-base.c", "instr": "i2c_adapter_depth(adap));"}, {"instr_func": "i2c_adapter_depth", "instr_loc": 1023, "instr_file": "drivers/i2c/i2c-core-base.c", "instr": "while ((adapter = i2c_parent_is_i2c_adapter(adapter)))"}], "at_file": "./include/linux/i2c.h", "by": "GlobalVariableRaceDetector says:", "at_func": "i2c_parent_is_i2c_adapter"}, "warn_no": 1}]}]}