{"all_contexts":[
{"num_warnings": 1,
"context":[{"lineno": -1, "instr": "  %4 = alloca %struct.file.4935*, align 8"}, {"lineno": 172, "file": "drivers/media/pci/saa7164/saa7164-vbi.c", "instr": "return saa7164_s_input(fh->port->enc_port, i);"}],
"warnings":[{"warn_data": {"at_line": 289, "warn_str": "Trying to use a global variable without locking.", "at": "dprintk(DBGLVL_ENC, \"%s() input=%d\\n\", __func__, i);", "inst_trace": [{"instr_func": "vidioc_s_input.1733", "instr_loc": -1, "instr": "  %4 = alloca %struct.file.4935*, align 8"}, {"instr_func": "vidioc_s_input.1733", "instr_loc": 172, "instr_file": "drivers/media/pci/saa7164/saa7164-vbi.c", "instr": "return saa7164_s_input(fh->port->enc_port, i);"}], "at_file": "drivers/media/pci/saa7164/saa7164-encoder.c", "by": "GlobalVariableRaceDetector says:", "at_func": "saa7164_s_input"}, "warn_no": 1}]},
{"num_warnings": 1,
"context":[{"lineno": -1, "instr": "  %4 = alloca %struct.file.4935*, align 8"}, {"lineno": 172, "file": "drivers/media/pci/saa7164/saa7164-vbi.c", "instr": "return saa7164_s_input(fh->port->enc_port, i);"}, {"lineno": 296, "file": "drivers/media/pci/saa7164/saa7164-encoder.c", "instr": "if (saa7164_api_set_videomux(port) != SAA_OK)"}],
"warnings":[{"warn_data": {"at_line": 428, "warn_str": "Trying to use a global variable without locking.", "at": "dprintk(DBGLVL_ENC, \"%s() v_mux=%d a_mux=%d\\n\",", "inst_trace": [{"instr_func": "vidioc_s_input.1733", "instr_loc": -1, "instr": "  %4 = alloca %struct.file.4935*, align 8"}, {"instr_func": "vidioc_s_input.1733", "instr_loc": 172, "instr_file": "drivers/media/pci/saa7164/saa7164-vbi.c", "instr": "return saa7164_s_input(fh->port->enc_port, i);"}, {"instr_func": "saa7164_s_input", "instr_loc": 296, "instr_file": "drivers/media/pci/saa7164/saa7164-encoder.c", "instr": "if (saa7164_api_set_videomux(port) != SAA_OK)"}], "at_file": "drivers/media/pci/saa7164/saa7164-api.c", "by": "GlobalVariableRaceDetector says:", "at_func": "saa7164_api_set_videomux"}, "warn_no": 1}]},
{"num_warnings": 1,
"context":[{"lineno": -1, "instr": "  %4 = alloca %struct.file.4935*, align 8"}, {"lineno": 172, "file": "drivers/media/pci/saa7164/saa7164-vbi.c", "instr": "return saa7164_s_input(fh->port->enc_port, i);"}, {"lineno": 296, "file": "drivers/media/pci/saa7164/saa7164-encoder.c", "instr": "if (saa7164_api_set_videomux(port) != SAA_OK)"}, {"lineno": 432, "file": "drivers/media/pci/saa7164/saa7164-api.c", "instr": "ret = saa7164_api_audio_mute(port, 1);"}],
"warnings":[{"warn_data": {"at_line": 463, "warn_str": "Trying to use a global variable without locking.", "at": "dprintk(DBGLVL_API, \"%s(%d)\\n\", __func__, mute);", "inst_trace": [{"instr_func": "vidioc_s_input.1733", "instr_loc": -1, "instr": "  %4 = alloca %struct.file.4935*, align 8"}, {"instr_func": "vidioc_s_input.1733", "instr_loc": 172, "instr_file": "drivers/media/pci/saa7164/saa7164-vbi.c", "instr": "return saa7164_s_input(fh->port->enc_port, i);"}, {"instr_func": "saa7164_s_input", "instr_loc": 296, "instr_file": "drivers/media/pci/saa7164/saa7164-encoder.c", "instr": "if (saa7164_api_set_videomux(port) != SAA_OK)"}, {"instr_func": "saa7164_api_set_videomux", "instr_loc": 432, "instr_file": "drivers/media/pci/saa7164/saa7164-api.c", "instr": "ret = saa7164_api_audio_mute(port, 1);"}], "at_file": "drivers/media/pci/saa7164/saa7164-api.c", "by": "GlobalVariableRaceDetector says:", "at_func": "saa7164_api_audio_mute"}, "warn_no": 1}]},
{"num_warnings": 1,
"context":[{"lineno": -1, "instr": "  %4 = alloca %struct.file.4935*, align 8"}, {"lineno": 172, "file": "drivers/media/pci/saa7164/saa7164-vbi.c", "instr": "return saa7164_s_input(fh->port->enc_port, i);"}, {"lineno": 296, "file": "drivers/media/pci/saa7164/saa7164-encoder.c", "instr": "if (saa7164_api_set_videomux(port) != SAA_OK)"}, {"lineno": 432, "file": "drivers/media/pci/saa7164/saa7164-api.c", "instr": "ret = saa7164_api_audio_mute(port, 1);"}, {"lineno": 465, "file": "drivers/media/pci/saa7164/saa7164-api.c", "instr": "ret = saa7164_cmd_send(port->dev, port->audfeat.unitid, SET_CUR,"}],
"warnings":[{"warn_data": {"at_line": 339, "warn_str": "Trying to use a global variable without locking.", "at": "dprintk(DBGLVL_CMD, \"%s(unitid = %s (%d) , command = 0x%x, sel = 0x%x)\\n\",", "inst_trace": [{"instr_func": "vidioc_s_input.1733", "instr_loc": -1, "instr": "  %4 = alloca %struct.file.4935*, align 8"}, {"instr_func": "vidioc_s_input.1733", "instr_loc": 172, "instr_file": "drivers/media/pci/saa7164/saa7164-vbi.c", "instr": "return saa7164_s_input(fh->port->enc_port, i);"}, {"instr_func": "saa7164_s_input", "instr_loc": 296, "instr_file": "drivers/media/pci/saa7164/saa7164-encoder.c", "instr": "if (saa7164_api_set_videomux(port) != SAA_OK)"}, {"instr_func": "saa7164_api_set_videomux", "instr_loc": 432, "instr_file": "drivers/media/pci/saa7164/saa7164-api.c", "instr": "ret = saa7164_api_audio_mute(port, 1);"}, {"instr_func": "saa7164_api_audio_mute", "instr_loc": 465, "instr_file": "drivers/media/pci/saa7164/saa7164-api.c", "instr": "ret = saa7164_cmd_send(port->dev, port->audfeat.unitid, SET_CUR,"}], "at_file": "drivers/media/pci/saa7164/saa7164-cmd.c", "by": "GlobalVariableRaceDetector says:", "at_func": "saa7164_cmd_send"}, "warn_no": 1}]},
{"num_warnings": 1,
"context":[{"lineno": -1, "instr": "  %4 = alloca %struct.file.4935*, align 8"}, {"lineno": 172, "file": "drivers/media/pci/saa7164/saa7164-vbi.c", "instr": "return saa7164_s_input(fh->port->enc_port, i);"}, {"lineno": 296, "file": "drivers/media/pci/saa7164/saa7164-encoder.c", "instr": "if (saa7164_api_set_videomux(port) != SAA_OK)"}, {"lineno": 432, "file": "drivers/media/pci/saa7164/saa7164-api.c", "instr": "ret = saa7164_api_audio_mute(port, 1);"}, {"lineno": 465, "file": "drivers/media/pci/saa7164/saa7164-api.c", "instr": "ret = saa7164_cmd_send(port->dev, port->audfeat.unitid, SET_CUR,"}, {"lineno": 339, "file": "drivers/media/pci/saa7164/saa7164-cmd.c", "instr": "dprintk(DBGLVL_CMD, \"%s(unitid = %s (%d) , command = 0x%x, sel = 0x%x)\\n\","}],
"warnings":[{"warn_data": {"at_line": 932, "warn_str": "Trying to use a global variable without locking.", "at": "unit = &saa7164_boards[dev->board].unit[i];", "inst_trace": [{"instr_func": "vidioc_s_input.1733", "instr_loc": -1, "instr": "  %4 = alloca %struct.file.4935*, align 8"}, {"instr_func": "vidioc_s_input.1733", "instr_loc": 172, "instr_file": "drivers/media/pci/saa7164/saa7164-vbi.c", "instr": "return saa7164_s_input(fh->port->enc_port, i);"}, {"instr_func": "saa7164_s_input", "instr_loc": 296, "instr_file": "drivers/media/pci/saa7164/saa7164-encoder.c", "instr": "if (saa7164_api_set_videomux(port) != SAA_OK)"}, {"instr_func": "saa7164_api_set_videomux", "instr_loc": 432, "instr_file": "drivers/media/pci/saa7164/saa7164-api.c", "instr": "ret = saa7164_api_audio_mute(port, 1);"}, {"instr_func": "saa7164_api_audio_mute", "instr_loc": 465, "instr_file": "drivers/media/pci/saa7164/saa7164-api.c", "instr": "ret = saa7164_cmd_send(port->dev, port->audfeat.unitid, SET_CUR,"}, {"instr_func": "saa7164_cmd_send", "instr_loc": 339, "instr_file": "drivers/media/pci/saa7164/saa7164-cmd.c", "instr": "dprintk(DBGLVL_CMD, \"%s(unitid = %s (%d) , command = 0x%x, sel = 0x%x)\\n\","}], "at_file": "drivers/media/pci/saa7164/saa7164-cards.c", "by": "GlobalVariableRaceDetector says:", "at_func": "saa7164_unitid_name"}, "warn_no": 1}]},
{"num_warnings": 1,
"context":[{"lineno": -1, "instr": "  %4 = alloca %struct.file.4935*, align 8"}, {"lineno": 172, "file": "drivers/media/pci/saa7164/saa7164-vbi.c", "instr": "return saa7164_s_input(fh->port->enc_port, i);"}, {"lineno": 296, "file": "drivers/media/pci/saa7164/saa7164-encoder.c", "instr": "if (saa7164_api_set_videomux(port) != SAA_OK)"}, {"lineno": 432, "file": "drivers/media/pci/saa7164/saa7164-api.c", "instr": "ret = saa7164_api_audio_mute(port, 1);"}, {"lineno": 465, "file": "drivers/media/pci/saa7164/saa7164-api.c", "instr": "ret = saa7164_cmd_send(port->dev, port->audfeat.unitid, SET_CUR,"}, {"lineno": 550, "file": "drivers/media/pci/saa7164/saa7164-cmd.c", "instr": "if (saa7164_cmd_dequeue(dev) != SAA_OK)"}],
"warnings":[{"warn_data": {"at_line": 127, "warn_str": "Trying to use a global variable without locking.", "at": "dprintk(DBGLVL_CMD, \"%s()\\n\", __func__);", "inst_trace": [{"instr_func": "vidioc_s_input.1733", "instr_loc": -1, "instr": "  %4 = alloca %struct.file.4935*, align 8"}, {"instr_func": "vidioc_s_input.1733", "instr_loc": 172, "instr_file": "drivers/media/pci/saa7164/saa7164-vbi.c", "instr": "return saa7164_s_input(fh->port->enc_port, i);"}, {"instr_func": "saa7164_s_input", "instr_loc": 296, "instr_file": "drivers/media/pci/saa7164/saa7164-encoder.c", "instr": "if (saa7164_api_set_videomux(port) != SAA_OK)"}, {"instr_func": "saa7164_api_set_videomux", "instr_loc": 432, "instr_file": "drivers/media/pci/saa7164/saa7164-api.c", "instr": "ret = saa7164_api_audio_mute(port, 1);"}, {"instr_func": "saa7164_api_audio_mute", "instr_loc": 465, "instr_file": "drivers/media/pci/saa7164/saa7164-api.c", "instr": "ret = saa7164_cmd_send(port->dev, port->audfeat.unitid, SET_CUR,"}, {"instr_func": "saa7164_cmd_send", "instr_loc": 550, "instr_file": "drivers/media/pci/saa7164/saa7164-cmd.c", "instr": "if (saa7164_cmd_dequeue(dev) != SAA_OK)"}], "at_file": "drivers/media/pci/saa7164/saa7164-cmd.c", "by": "GlobalVariableRaceDetector says:", "at_func": "saa7164_cmd_dequeue"}, "warn_no": 1}]},
{"num_warnings": 1,
"context":[{"lineno": -1, "instr": "  %4 = alloca %struct.file.4935*, align 8"}, {"lineno": 172, "file": "drivers/media/pci/saa7164/saa7164-vbi.c", "instr": "return saa7164_s_input(fh->port->enc_port, i);"}, {"lineno": 296, "file": "drivers/media/pci/saa7164/saa7164-encoder.c", "instr": "if (saa7164_api_set_videomux(port) != SAA_OK)"}, {"lineno": 432, "file": "drivers/media/pci/saa7164/saa7164-api.c", "instr": "ret = saa7164_api_audio_mute(port, 1);"}, {"lineno": 465, "file": "drivers/media/pci/saa7164/saa7164-api.c", "instr": "ret = saa7164_cmd_send(port->dev, port->audfeat.unitid, SET_CUR,"}, {"lineno": 398, "file": "drivers/media/pci/saa7164/saa7164-cmd.c", "instr": "ret = saa7164_cmd_wait(dev, pcommand_t->seqno);"}],
"warnings":[{"warn_data": {"at_line": 252, "warn_str": "Trying to use a global variable without locking.", "at": "if (saa_debug >= 4)", "inst_trace": [{"instr_func": "vidioc_s_input.1733", "instr_loc": -1, "instr": "  %4 = alloca %struct.file.4935*, align 8"}, {"instr_func": "vidioc_s_input.1733", "instr_loc": 172, "instr_file": "drivers/media/pci/saa7164/saa7164-vbi.c", "instr": "return saa7164_s_input(fh->port->enc_port, i);"}, {"instr_func": "saa7164_s_input", "instr_loc": 296, "instr_file": "drivers/media/pci/saa7164/saa7164-encoder.c", "instr": "if (saa7164_api_set_videomux(port) != SAA_OK)"}, {"instr_func": "saa7164_api_set_videomux", "instr_loc": 432, "instr_file": "drivers/media/pci/saa7164/saa7164-api.c", "instr": "ret = saa7164_api_audio_mute(port, 1);"}, {"instr_func": "saa7164_api_audio_mute", "instr_loc": 465, "instr_file": "drivers/media/pci/saa7164/saa7164-api.c", "instr": "ret = saa7164_cmd_send(port->dev, port->audfeat.unitid, SET_CUR,"}, {"instr_func": "saa7164_cmd_send", "instr_loc": 398, "instr_file": "drivers/media/pci/saa7164/saa7164-cmd.c", "instr": "ret = saa7164_cmd_wait(dev, pcommand_t->seqno);"}], "at_file": "drivers/media/pci/saa7164/saa7164-cmd.c", "by": "GlobalVariableRaceDetector says:", "at_func": "saa7164_cmd_wait"}, "warn_no": 1}]},
{"num_warnings": 1,
"context":[{"lineno": -1, "instr": "  %4 = alloca %struct.file.4935*, align 8"}, {"lineno": 172, "file": "drivers/media/pci/saa7164/saa7164-vbi.c", "instr": "return saa7164_s_input(fh->port->enc_port, i);"}, {"lineno": 296, "file": "drivers/media/pci/saa7164/saa7164-encoder.c", "instr": "if (saa7164_api_set_videomux(port) != SAA_OK)"}, {"lineno": 437, "file": "drivers/media/pci/saa7164/saa7164-api.c", "instr": "ret = saa7164_cmd_send(port->dev, port->vidproc.sourceid, SET_CUR,"}, {"lineno": 537, "file": "drivers/media/pci/saa7164/saa7164-cmd.c", "instr": "ret = saa7164_bus_get(dev, presponse_t, buf + data_recd, 0);"}, {"lineno": 314, "file": "drivers/media/pci/saa7164/saa7164-bus.c", "instr": "saa7164_bus_verify(dev);"}],
"warnings":[{"warn_data": {"at_line": 88, "warn_str": "Trying to use a global variable without locking.", "at": "saa_debug = 0xffff; /* Ensure we get the bus dump */", "inst_trace": [{"instr_func": "vidioc_s_input.1733", "instr_loc": -1, "instr": "  %4 = alloca %struct.file.4935*, align 8"}, {"instr_func": "vidioc_s_input.1733", "instr_loc": 172, "instr_file": "drivers/media/pci/saa7164/saa7164-vbi.c", "instr": "return saa7164_s_input(fh->port->enc_port, i);"}, {"instr_func": "saa7164_s_input", "instr_loc": 296, "instr_file": "drivers/media/pci/saa7164/saa7164-encoder.c", "instr": "if (saa7164_api_set_videomux(port) != SAA_OK)"}, {"instr_func": "saa7164_api_set_videomux", "instr_loc": 437, "instr_file": "drivers/media/pci/saa7164/saa7164-api.c", "instr": "ret = saa7164_cmd_send(port->dev, port->vidproc.sourceid, SET_CUR,"}, {"instr_func": "saa7164_cmd_send", "instr_loc": 537, "instr_file": "drivers/media/pci/saa7164/saa7164-cmd.c", "instr": "ret = saa7164_bus_get(dev, presponse_t, buf + data_recd, 0);"}, {"instr_func": "saa7164_bus_get", "instr_loc": 314, "instr_file": "drivers/media/pci/saa7164/saa7164-bus.c", "instr": "saa7164_bus_verify(dev);"}], "at_file": "drivers/media/pci/saa7164/saa7164-bus.c", "by": "GlobalVariableRaceDetector says:", "at_func": "saa7164_bus_verify"}, "warn_no": 1}]},
{"num_warnings": 1,
"context":[{"lineno": -1, "instr": "  %4 = alloca %struct.file.4935*, align 8"}, {"lineno": 172, "file": "drivers/media/pci/saa7164/saa7164-vbi.c", "instr": "return saa7164_s_input(fh->port->enc_port, i);"}, {"lineno": 296, "file": "drivers/media/pci/saa7164/saa7164-encoder.c", "instr": "if (saa7164_api_set_videomux(port) != SAA_OK)"}, {"lineno": 437, "file": "drivers/media/pci/saa7164/saa7164-api.c", "instr": "ret = saa7164_cmd_send(port->dev, port->vidproc.sourceid, SET_CUR,"}, {"lineno": 398, "file": "drivers/media/pci/saa7164/saa7164-cmd.c", "instr": "ret = saa7164_cmd_wait(dev, pcommand_t->seqno);"}, {"lineno": 253, "file": "drivers/media/pci/saa7164/saa7164-cmd.c", "instr": "saa7164_bus_dump(dev);"}],
"warnings":[{"warn_data": {"at_line": 46, "warn_str": "Trying to use a global variable without locking.", "at": "dprintk(DBGLVL_BUS, \"Dumping the bus structure:\\n\");", "inst_trace": [{"instr_func": "vidioc_s_input.1733", "instr_loc": -1, "instr": "  %4 = alloca %struct.file.4935*, align 8"}, {"instr_func": "vidioc_s_input.1733", "instr_loc": 172, "instr_file": "drivers/media/pci/saa7164/saa7164-vbi.c", "instr": "return saa7164_s_input(fh->port->enc_port, i);"}, {"instr_func": "saa7164_s_input", "instr_loc": 296, "instr_file": "drivers/media/pci/saa7164/saa7164-encoder.c", "instr": "if (saa7164_api_set_videomux(port) != SAA_OK)"}, {"instr_func": "saa7164_api_set_videomux", "instr_loc": 437, "instr_file": "drivers/media/pci/saa7164/saa7164-api.c", "instr": "ret = saa7164_cmd_send(port->dev, port->vidproc.sourceid, SET_CUR,"}, {"instr_func": "saa7164_cmd_send", "instr_loc": 398, "instr_file": "drivers/media/pci/saa7164/saa7164-cmd.c", "instr": "ret = saa7164_cmd_wait(dev, pcommand_t->seqno);"}, {"instr_func": "saa7164_cmd_wait", "instr_loc": 253, "instr_file": "drivers/media/pci/saa7164/saa7164-cmd.c", "instr": "saa7164_bus_dump(dev);"}], "at_file": "drivers/media/pci/saa7164/saa7164-bus.c", "by": "GlobalVariableRaceDetector says:", "at_func": "saa7164_bus_dump"}, "warn_no": 1}]}]}